baseten_scaffolding/__init__.py
baseten_scaffolding/constants.py
baseten_scaffolding/definitions/__init__.py
baseten_scaffolding/definitions/base.py
baseten_scaffolding/definitions/custom.py
baseten_scaffolding/definitions/huggingface_transformer.py
baseten_scaffolding/definitions/keras.py
baseten_scaffolding/definitions/pytorch.py
baseten_scaffolding/definitions/sklearn.py
baseten_scaffolding/errors.py
baseten_scaffolding/model_inference.py
baseten_scaffolding/scaffold/__init__.py
baseten_scaffolding/scaffold/build.py
baseten_scaffolding/scaffold_templates/__init__.py
baseten_scaffolding/scaffold_templates/common/__init__.py
baseten_scaffolding/scaffold_templates/common/b10server.py
baseten_scaffolding/scaffold_templates/common/config.py
baseten_scaffolding/scaffold_templates/common/errors.py
baseten_scaffolding/scaffold_templates/common/lib_support.py
baseten_scaffolding/scaffold_templates/common/serialization.py
baseten_scaffolding/scaffold_templates/common/util.py
baseten_scaffolding/scaffold_templates/custom_server/__init__.py
baseten_scaffolding/scaffold_templates/custom_server/inference_server.py
baseten_scaffolding/scaffold_templates/custom_server/server/__init__.py
baseten_scaffolding/scaffold_templates/custom_server/server/inference_model.py
baseten_scaffolding/scaffold_templates/custom_server/server_requirements.txt
baseten_scaffolding/scaffold_templates/docker/custom-server-gpu.Dockerfile
baseten_scaffolding/scaffold_templates/docker/custom-server.Dockerfile
baseten_scaffolding/scaffold_templates/docker/huggingface_transformer-server-gpu.Dockerfile
baseten_scaffolding/scaffold_templates/docker/huggingface_transformer-server.Dockerfile
baseten_scaffolding/scaffold_templates/docker/keras-server-gpu.Dockerfile
baseten_scaffolding/scaffold_templates/docker/keras-server.Dockerfile
baseten_scaffolding/scaffold_templates/docker/pytorch-server-gpu.Dockerfile
baseten_scaffolding/scaffold_templates/docker/pytorch-server.Dockerfile
baseten_scaffolding-0.0.19.dist-info/WHEEL
baseten_scaffolding-0.0.19.dist-info/METADATA
baseten_scaffolding-0.0.19.dist-info/RECORD
