Metadata-Version: 2.1
Name: baseten-scaffolding
Version: 0.0.19
Summary: 
Author: Alex Gillmor
Author-email: alex@baseten.co
Requires-Python: >=3.7,<3.11
Classifier: Programming Language :: Python :: 3
Classifier: Programming Language :: Python :: 3.10
Classifier: Programming Language :: Python :: 3.7
Classifier: Programming Language :: Python :: 3.8
Classifier: Programming Language :: Python :: 3.9
Requires-Dist: PyYAML (>=6.0,<7.0)
Requires-Dist: msgpack (==1.0.2)
Requires-Dist: msgpack-numpy (==0.4.7.1)
Requires-Dist: numpy (>=1.18,<2.0)
Requires-Dist: packaging (==20.9)
Requires-Dist: python-json-logger (==2.0.2)
